edi_invoice_parser/__init__.py
edi_invoice_parser/cross_industry_invoice_mapper.py
edi_invoice_parser/cii_dom_parser/__init__.py
edi_invoice_parser/cii_dom_parser/dom_elements_helper.py
edi_invoice_parser/cii_dom_parser/pdf.py
edi_invoice_parser/cii_dom_parser/utils.py
edi_invoice_parser/cii_dom_parser/xml_cii_dom_parser.py
edi_invoice_parser/cii_dom_parser/xmp_schema.py
edi_invoice_parser/cii_dom_parser/models/__init__.py
edi_invoice_parser/cii_dom_parser/models/accounting.py
edi_invoice_parser/cii_dom_parser/models/container.py
edi_invoice_parser/cii_dom_parser/models/delivery.py
edi_invoice_parser/cii_dom_parser/models/document.py
edi_invoice_parser/cii_dom_parser/models/elements.py
edi_invoice_parser/cii_dom_parser/models/fields.py
edi_invoice_parser/cii_dom_parser/models/note.py
edi_invoice_parser/cii_dom_parser/models/party.py
edi_invoice_parser/cii_dom_parser/models/payment.py
edi_invoice_parser/cii_dom_parser/models/product.py
edi_invoice_parser/cii_dom_parser/models/references.py
edi_invoice_parser/cii_dom_parser/models/trade.py
edi_invoice_parser/cii_dom_parser/models/tradelines.py
edi_invoice_parser/model/__init__.py
edi_invoice_parser/model/trade_document_types.py
edi_invoice_parser/model/xml_abstract_x_rechnung_parser.py
edi_invoice_parser/tests/__init__.py
edi_invoice_parser/tests/test_iban_handling.py
edi_invoice_parser/tests/test_parse_x_rechnung.py
edi_invoice_parser/ubl_sax_parser/__init__.py
edi_invoice_parser/ubl_sax_parser/xml_ubl_sax_parser.py
edi_invoice_parser/util/__init__.py
edi_invoice_parser/util/file_helper.py
edi_invoice_parser/util/timer_helper.py
mikrowerk_edi_invoicing-0.6.6.dist-info/licenses/LICENSE
mikrowerk_edi_invoicing-0.6.6.dist-info/METADATA
mikrowerk_edi_invoicing-0.6.6.dist-info/WHEEL
mikrowerk_edi_invoicing-0.6.6.dist-info/top_level.txt
mikrowerk_edi_invoicing-0.6.6.dist-info/RECORD
