Metadata-Version: 2.4
Name: mikrowerk_edi_invoicing
Version: 0.6.6
Summary: Parser for EDI invoices in CII or UBL format or plain pdf with LLM support
Author: Mikrowerk a Gammadata Division
Author-email: info@mikrowerk.com
License: GNU Affero General Public License v3 
Classifier: Programming Language :: Python :: 3
Classifier: License :: OSI Approved :: GNU Affero General Public License v3 or later (AGPLv3+)
Classifier: Operating System :: OS Independent
License-File: LICENSE
Requires-Dist: lxml
Requires-Dist: pypdf
Requires-Dist: pytest
Requires-Dist: flake8
Requires-Dist: isort
Requires-Dist: black
Requires-Dist: coverage
Requires-Dist: codecov
Requires-Dist: factur-x==3.6
Requires-Dist: jsonpickle~=4.0.1
Requires-Dist: parameterized
Requires-Dist: schwifty
Requires-Dist: google-genai
Dynamic: author
Dynamic: author-email
Dynamic: classifier
Dynamic: description
Dynamic: description-content-type
Dynamic: license
Dynamic: license-file
Dynamic: requires-dist
Dynamic: summary
